bballRefWebScraper/__init__.py
bballRefWebScraper/bb_ref_scraper.py
bballRefWebScraper/draft_class.py
bballRefWebScraper/examples.py
bballRefWebScraper/get_player_stats.py
bballRefWebScraper/mvp_tracker.py
bballRefWebScraper/per_game_leaders.py
bballRefWebScraper/schedule.py
bballRefWebScraper/utils.py
bballRefWebScraper-0.1.0.dist-info/LICENSE
bballRefWebScraper-0.1.0.dist-info/METADATA
bballRefWebScraper-0.1.0.dist-info/WHEEL
bballRefWebScraper-0.1.0.dist-info/top_level.txt
bballRefWebScraper-0.1.0.dist-info/RECORD
