Metadata-Version: 2.1
Name: bballRefWebScraper
Version: 0.1.0
Summary: A package that Grabs basketball data from basketball-reference
Home-page: https://github.com/michaelc143/BballRefWebScraper
Author: Michael Corbishley
Author-email: corbishleymichael1@gmail.com
Maintainer: Michael Corbishley
Maintainer-email: corbishleymichael1@gmail.com
License: MIT
Classifier: Programming Language :: Python :: 3
Classifier: License :: OSI Approved :: MIT License
Classifier: Operating System :: OS Independent
Requires-Python: >=3.6
License-File: LICENSE
Requires-Dist: beautifulsoup4 (==4.12.2)
Requires-Dist: bs4 (==0.0.1)
Requires-Dist: lxml (==4.9.3)
Requires-Dist: numpy (==1.24.3)
Requires-Dist: pandas (==2.0.3)
Requires-Dist: unidecode (==1.2.0)
Requires-Dist: requests (==2.31.0)
Provides-Extra: test
Requires-Dist: pytest ; extra == 'test'
